imbrium/__init__.py
imbrium/architectures/__init__.py
imbrium/architectures/models.py
imbrium/blueprints/__init__.py
imbrium/blueprints/abstract_multivariate.py
imbrium/blueprints/abstract_univariate.py
imbrium/predictors/__init__.py
imbrium/predictors/multivarhybrid.py
imbrium/predictors/multivarpure.py
imbrium/predictors/univarhybrid.py
imbrium/predictors/univarpure.py
imbrium/utils/__init__.py
imbrium/utils/optimizer.py
imbrium/utils/transformer.py
imbrium-3.1.0.dist-info/LICENSE
imbrium-3.1.0.dist-info/METADATA
imbrium-3.1.0.dist-info/WHEEL
imbrium-3.1.0.dist-info/top_level.txt
imbrium-3.1.0.dist-info/RECORD
