Metadata-Version: 2.1
Name: imbrium
Version: 3.1.0
Summary: Standard and Hybrid Deep Learning Multivariate-Multi-Step & Univariate-Multi-Step Time Series Forecasting.
Home-page: https://github.com/maxmekiska/imbrium
Author: Maximilian Mekiska
Author-email: maxmekiska@gmail.com
License: UNKNOWN
Keywords: machinelearning,keras,deeplearning,timeseries,forecasting
Platform: UNKNOWN
Classifier: Programming Language :: Python :: 3.9
Classifier: Programming Language :: Python :: 3.10
Classifier: Programming Language :: Python :: 3.11
Classifier: Operating System :: Microsoft :: Windows
Classifier: Topic :: Scientific/Engineering :: Artificial Intelligence
License-File: LICENSE
Requires-Dist: setuptools >=41.0.0
Requires-Dist: tensorflow <2.17.0,>=2.16.0
